[
  { "nomePais": "Afeganistão" },
  { "nomePais": "África do Sul" },
  { "nomePais": "Albânia" },
  { "nomePais": "Alemanha" },
  { "nomePais": "Andorra" },
  { "nomePais": "Angola" },
  { "nomePais": "Anguilla" },
  { "nomePais": "Antártida" },
  { "nomePais": "Antígua e Barbuda" },
  { "nomePais": "Arábia Saudita" },
  { "nomePais": "Argélia" },
  { "nomePais": "Argentina" },
  { "nomePais": "Armênia" },
  { "nomePais": "Aruba" },
  { "nomePais": "Austrália" },
  { "nomePais": "Áustria" },
  { "nomePais": "Azerbaijão" },
  { "nomePais": "Bahamas" },
  { "nomePais": "Bahrein" },
  { "nomePais": "Bangladesh" },
  { "nomePais": "Barbados" },
  { "nomePais": "Belarus" },
  { "nomePais": "Bélgica" },
  { "nomePais": "Belize" },
  { "nomePais": "Benin" },
  { "nomePais": "Bermudas" },
  { "nomePais": "Bolívia" },
  { "nomePais": "Bósnia-Herzegóvina" },
  { "nomePais": "Botsuana" },
  { "nomePais": "Brasil" },
  { "nomePais": "Brunei" },
  { "nomePais": "Bulgária" },
  { "nomePais": "Burkina Fasso" },
  { "nomePais": "Burundi" },
  { "nomePais": "Butão" },
  { "nomePais": "Cabo Verde" },
  { "nomePais": "Camarões" },
  { "nomePais": "Camboja" },
  { "nomePais": "Canadá" },
  { "nomePais": "Canárias" },
  { "nomePais": "Cazaquistão" },
  { "nomePais": "Ceuta e Melilla" },
  { "nomePais": "Chade" },
  { "nomePais": "Chile" },
  { "nomePais": "China" },
  { "nomePais": "Chipre" },
  { "nomePais": "Cingapura" },
  { "nomePais": "Colômbia" },
  { "nomePais": "Comores" },
  { "nomePais": "Congo" },
  { "nomePais": "Coréia do Norte" },
  { "nomePais": "Coréia do Sul" },
  { "nomePais": "Costa do Marfim" },
  { "nomePais": "Costa Rica" },
  { "nomePais": "Croácia" },
  { "nomePais": "Cuba" },
  { "nomePais": "Curaçao" },
  { "nomePais": "Diego Garcia" },
  { "nomePais": "Dinamarca" },
  { "nomePais": "Djibuti" },
  { "nomePais": "Dominica" },
  { "nomePais": "Egito" },
  { "nomePais": "El Salvador" },
  { "nomePais": "Emirados Árabes Unidos" },
  { "nomePais": "Equador" },
  { "nomePais": "Eritréia" },
  { "nomePais": "Eslováquia" },
  { "nomePais": "Eslovênia" },
  { "nomePais": "Espanha" },
  { "nomePais": "Estados Unidos" },
  { "nomePais": "Estônia" },
  { "nomePais": "Etiópia" },
  { "nomePais": "Fiji" },
  { "nomePais": "Filipinas" },
  { "nomePais": "Finlândia" },
  { "nomePais": "França" },
  { "nomePais": "Gabão" },
  { "nomePais": "Gâmbia" },
  { "nomePais": "Gana" },
  { "nomePais": "Geórgia" },
  { "nomePais": "Gibraltar" },
  { "nomePais": "Grã-Bretanha (Reino Unido, UK)" },
  { "nomePais": "Granada" },
  { "nomePais": "Grécia" },
  { "nomePais": "Groelândia" },
  { "nomePais": "Guadalupe" },
  { "nomePais": "Guam (Território dos Estados Unidos)" },
  { "nomePais": "Guatemala" },
  { "nomePais": "Guernsey" },
  { "nomePais": "Guiana" },
  { "nomePais": "Guiana Francesa" },
  { "nomePais": "Guiné" },
  { "nomePais": "Guiné Equatorial" },
  { "nomePais": "Guiné-Bissau" },
  { "nomePais": "Haiti" },
  { "nomePais": "Holanda" },
  { "nomePais": "Honduras" },
  { "nomePais": "Hong Kong" },
  { "nomePais": "Hungria" },
  { "nomePais": "Iêmen" },
  { "nomePais": "Ilha Bouvet" },
  { "nomePais": "Ilha de Ascensão" },
  { "nomePais": "Ilha de Clipperton" },
  { "nomePais": "Ilha de Man" },
  { "nomePais": "Ilha Natal" },
  { "nomePais": "Ilha Pitcairn" },
  { "nomePais": "Ilha Reunião" },
  { "nomePais": "Ilhas Aland" },
  { "nomePais": "Ilhas Cayman" },
  { "nomePais": "Ilhas Cocos" },
  { "nomePais": "Ilhas Cook" },
  { "nomePais": "Ilhas Faroes" },
  { "nomePais": "Ilhas Geórgia do Sul e Sandwich do Sul" },
  { "nomePais": "Ilhas Heard e McDonald (Território da Austrália)" },
  { "nomePais": "Ilhas Malvinas" },
  { "nomePais": "Ilhas Marianas do Norte" },
  { "nomePais": "Ilhas Marshall" },
  { "nomePais": "Ilhas Menores dos Estados Unidos" },
  { "nomePais": "Ilhas Norfolk" },
  { "nomePais": "Ilhas Salomão" },
  { "nomePais": "Ilhas Seychelles" },
  { "nomePais": "Ilhas Tokelau" },
  { "nomePais": "Ilhas Turks e Caicos" },
  { "nomePais": "Ilhas Virgens (Estados Unidos)" },
  { "nomePais": "Ilhas Virgens (Inglaterra)" },
  { "nomePais": "Índia" },
  { "nomePais": "Indonésia" },
  { "nomePais": "Irã" },
  { "nomePais": "Iraque" },
  { "nomePais": "Irlanda" },
  { "nomePais": "Islândia" },
  { "nomePais": "Israel" },
  { "nomePais": "Itália" },
  { "nomePais": "Jamaica" },
  { "nomePais": "Japão" },
  { "nomePais": "Jersey" },
  { "nomePais": "Jordânia" },
  { "nomePais": "Kiribati" },
  { "nomePais": "Kosovo" },
  { "nomePais": "Kuait" },
  { "nomePais": "Laos" },
  { "nomePais": "Lesoto" },
  { "nomePais": "Letônia" },
  { "nomePais": "Líbano" },
  { "nomePais": "Libéria" },
  { "nomePais": "Líbia" },
  { "nomePais": "Liechtenstein" },
  { "nomePais": "Lituânia" },
  { "nomePais": "Luxemburgo" },
  { "nomePais": "Macau" },
  { "nomePais": "Macedônia (República Yugoslava)" },
  { "nomePais": "Madagascar" },
  { "nomePais": "Malásia" },
  { "nomePais": "Malaui" },
  { "nomePais": "Maldivas" },
  { "nomePais": "Mali" },
  { "nomePais": "Malta" },
  { "nomePais": "Marrocos" },
  { "nomePais": "Martinica" },
  { "nomePais": "Maurício" },
  { "nomePais": "Mauritânia" },
  { "nomePais": "Mayotte" },
  { "nomePais": "México" },
  { "nomePais": "Micronésia" },
  { "nomePais": "Moçambique" },
  { "nomePais": "Moldova" },
  { "nomePais": "Mônaco" },
  { "nomePais": "Mongólia" },
  { "nomePais": "Montenegro" },
  { "nomePais": "Montserrat" },
  { "nomePais": "Myanma" },
  { "nomePais": "Namíbia" },
  { "nomePais": "Nauru" },
  { "nomePais": "Nepal" },
  { "nomePais": "Nicarágua" },
  { "nomePais": "Níger" },
  { "nomePais": "Nigéria" },
  { "nomePais": "Niue" },
  { "nomePais": "Noruega" },
  { "nomePais": "Nova Caledônia" },
  { "nomePais": "Nova Zelândia" },
  { "nomePais": "Omã" },
  { "nomePais": "Países Baixos Caribenhos" },
  { "nomePais": "Palau" },
  { "nomePais": "Palestina" },
  { "nomePais": "Panamá" },
  { "nomePais": "Papua-Nova Guiné" },
  { "nomePais": "Paquistão" },
  { "nomePais": "Paraguai" },
  { "nomePais": "Peru" },
  { "nomePais": "Polinésia Francesa" },
  { "nomePais": "Polônia" },
  { "nomePais": "Porto Rico" },
  { "nomePais": "Portugal" },
  { "nomePais": "Qatar" },
  { "nomePais": "Quênia" },
  { "nomePais": "Quirguistão" },
  { "nomePais": "República Centro-Africana" },
  { "nomePais": "República Democrática do Congo" },
  { "nomePais": "República Dominicana" },
  { "nomePais": "República Tcheca" },
  { "nomePais": "Romênia" },
  { "nomePais": "Ruanda" },
  { "nomePais": "Rússia (antiga URSS) - Federação Russa" },
  { "nomePais": "Saara Ocidental" },
  { "nomePais": "Saint-Pierre e Miquelon" },
  { "nomePais": "Samoa Americana" },
  { "nomePais": "Samoa Ocidental" },
  { "nomePais": "San Marino" },
  { "nomePais": "Santa Helena" },
  { "nomePais": "Santa Lúcia" },
  { "nomePais": "São Bartolomeu" },
  { "nomePais": "São Cristóvão e Névis" },
  { "nomePais": "São Martim" },
  { "nomePais": "São Martinho" },
  { "nomePais": "São Tomé e Príncipe" },
  { "nomePais": "São Vicente e Granadinas" },
  { "nomePais": "Senegal" },
  { "nomePais": "Serra Leoa" },
  { "nomePais": "Sérvia" },
  { "nomePais": "Síria" },
  { "nomePais": "Somália" },
  { "nomePais": "Sri Lanka" },
  { "nomePais": "Suazilândia" },
  { "nomePais": "Sudão" },
  { "nomePais": "Sudão do Sul" },
  { "nomePais": "Suécia" },
  { "nomePais": "Suíça" },
  { "nomePais": "Suriname" },
  { "nomePais": "Svalbard" },
  { "nomePais": "Tadjiquistão" },
  { "nomePais": "Tailândia" },
  { "nomePais": "Taiwan" },
  { "nomePais": "Tanzânia" },
  { "nomePais": "Território Britânico do Oceano índico" },
  { "nomePais": "Territórios do Sul da França" },
  { "nomePais": "Timor-Leste" },
  { "nomePais": "Togo" },
  { "nomePais": "Tonga" },
  { "nomePais": "Trinidad e Tobago" },
  { "nomePais": "Tristão da Cunha" },
  { "nomePais": "Tunísia" },
  { "nomePais": "Turcomenistão" },
  { "nomePais": "Turquia" },
  { "nomePais": "Tuvalu" },
  { "nomePais": "Ucrânia" },
  { "nomePais": "Uganda" },
  { "nomePais": "Uruguai" },
  { "nomePais": "Uzbequistão" },
  { "nomePais": "Vanuatu" },
  { "nomePais": "Vaticano" },
  { "nomePais": "Venezuela" },
  { "nomePais": "Vietnã" },
  { "nomePais": "Wallis e Futuna" },
  { "nomePais": "Zâmbia" },
  { "nomePais": "Zimbábue" }
]
